sureverify/__init__.py
sureverify/_base_client.py
sureverify/_client.py
sureverify/_compat.py
sureverify/_constants.py
sureverify/_exceptions.py
sureverify/_files.py
sureverify/_models.py
sureverify/_qs.py
sureverify/_resource.py
sureverify/_response.py
sureverify/_streaming.py
sureverify/_types.py
sureverify/_version.py
sureverify/pagination.py
sureverify/py.typed
sureverify/_utils/__init__.py
sureverify/_utils/_logs.py
sureverify/_utils/_proxy.py
sureverify/_utils/_reflection.py
sureverify/_utils/_streams.py
sureverify/_utils/_sync.py
sureverify/_utils/_transform.py
sureverify/_utils/_typing.py
sureverify/_utils/_utils.py
sureverify/lib/.keep
sureverify/lib/__init__.py
sureverify/lib/auth.py
sureverify/lib/file_upload.py
sureverify/resources/__init__.py
sureverify/resources/addresses.py
sureverify/resources/attachments.py
sureverify/resources/communities.py
sureverify/resources/policies.py
sureverify/resources/property_managers.py
sureverify/resources/residents.py
sureverify/resources/units.py
sureverify/resources/verification_case_inputs.py
sureverify/resources/verification_portal_links.py
sureverify/resources/verification_portals.py
sureverify/resources/verification_sessions.py
sureverify/resources/webhook_endpoints.py
sureverify/resources/verification_cases/__init__.py
sureverify/resources/verification_cases/update_status.py
sureverify/resources/verification_cases/verification_cases.py
sureverify/types/__init__.py
sureverify/types/address.py
sureverify/types/address_create_params.py
sureverify/types/address_list_params.py
sureverify/types/address_request_data_param.py
sureverify/types/address_request_param.py
sureverify/types/address_response.py
sureverify/types/address_retrieve_params.py
sureverify/types/address_update_params.py
sureverify/types/attachment_create_params.py
sureverify/types/attachment_create_response.py
sureverify/types/community.py
sureverify/types/community_create_params.py
sureverify/types/community_list_params.py
sureverify-0.1.0a10.dist-info/METADATA
sureverify-0.1.0a10.dist-info/WHEEL
sureverify-0.1.0a10.dist-info/licenses/LICENSE
sureverify-0.1.0a10.dist-info/RECORD
