Metadata-Version: 2.3
Name: sureverify
Version: 0.1.0a10
Summary: The official Python library for the verify API
Project-URL: Homepage, https://github.com/sureapp/verify-python
Project-URL: Repository, https://github.com/sureapp/verify-python
Author-email: Verify <support@sureverify.com>
License: Apache-2.0
Classifier: Intended Audience :: Developers
Classifier: License :: OSI Approved :: Apache Software License
Classifier: Operating System :: MacOS
Classifier: Operating System :: Microsoft :: Windows
Classifier: Operating System :: OS Independent
Classifier: Operating System :: POSIX
Classifier: Operating System :: POSIX :: Linux
Classifier: Programming Language :: Python :: 3.8
Classifier: Programming Language :: Python :: 3.9
Classifier: Programming Language :: Python :: 3.10
Classifier: Programming Language :: Python :: 3.11
Classifier: Programming Language :: Python :: 3.12
Classifier: Topic :: Software Development :: Libraries :: Python Modules
Classifier: Typing :: Typed
Requires-Python: >=3.8
Requires-Dist: anyio<5,>=3.5.0
Requires-Dist: cryptography>=44.0.2
Requires-Dist: distro<2,>=1.7.0
Requires-Dist: httpx<1,>=0.23.0
Requires-Dist: pydantic<3,>=1.9.0
Requires-Dist: pyjwt>=2.10.1
Requires-Dist: sniffio
Requires-Dist: typing-extensions<5,>=4.10
